pykhipu/__init__.py
pykhipu/banks.py
pykhipu/client.py
pykhipu/errors.py
pykhipu/items.py
pykhipu/payments.py
pykhipu/receivers.py
pykhipu/responses.py
pykhipu-0.1.9.dist-info/LICENSE.txt
pykhipu-0.1.9.dist-info/WHEEL
pykhipu-0.1.9.dist-info/METADATA
pykhipu-0.1.9.dist-info/RECORD
